send2airgap/__init__.py
send2airgap/__main__.py
send2airgap/base.py
send2airgap/cli.py
send2airgap-0.1.0.dist-info/LICENSE
send2airgap-0.1.0.dist-info/METADATA
send2airgap-0.1.0.dist-info/WHEEL
send2airgap-0.1.0.dist-info/entry_points.txt
send2airgap-0.1.0.dist-info/top_level.txt
send2airgap-0.1.0.dist-info/RECORD
